xword/__init__.py
xword/aes/__init__.py
xword/aes/_fmtdata.py
xword/aes/cryptor.py
xword/requests/__init__.py
xword/requests/base.py
xword/requests/export.py
xword/requests/sessions.py
xword/requests/utils.py
xword-1.0.2.dist-info/LICENSE
xword-1.0.2.dist-info/METADATA
xword-1.0.2.dist-info/WHEEL
xword-1.0.2.dist-info/top_level.txt
xword-1.0.2.dist-info/RECORD
