Metadata-Version: 2.1
Name: xword
Version: 1.0.2
Home-page: 
Author: PengKe
Author-email: 925330867@qq.com
Classifier: Programming Language :: Python :: 3
Classifier: License :: OSI Approved :: MIT License
Classifier: Operating System :: OS Independent
Requires-Python: >=3.8
License-File: LICENSE
Requires-Dist: requests
Requires-Dist: yarl
Requires-Dist: rich
